{"workouts":[{
    "id":0,
    "name":"Anthony",
    "level": 1,
    "for": "Ganzkörper",
    "roundsExercises": "6x3",
    "exercises":[
        {"id":0, "round": 1, "name": "Start in", "duration": 10, "vis":false},{"id":1,  "round": 1, "name":"Mountain Jumpers", "duration":30,"vis": true, "link":""},
        {"id":0, "round": 1, "name": "Recovery", "duration": 20, "vis":false},{"id":2,  "round": 1, "name":"Crunches", "duration":45,"vis": true, "link":""},
        {"id":0, "round": 1, "name": "Recovery", "duration": 20, "vis":false},{"id":3,  "round": 1, "name":"Easy Squats", "duration":30,"vis": true, "link":"https://www.youtube.com/watch?v=2uaMnEg89bU"},
        {"id":0, "round": 1, "name": "Recovery", "duration": 20, "vis":false},{"id":4,  "round": 2, "name":"Mountain Climbers", "duration":30,"vis": true, "link":"https://www.youtube.com/watch?v=2uaMnEg89bU"},
        {"id":0, "round": 1, "name": "Recovery", "duration": 20, "vis":false},{"id":5,  "round": 2, "name":"Crunches", "duration":45,"vis": true, "link":"https://www.youtube.com/watch?v=2uaMnEg89bU"},
        {"id":0, "round": 1, "name": "Recovery", "duration": 20, "vis":false},{"id":6,  "round": 2, "name":"Easy Squats", "duration":30,"vis": true, "link":"https://www.youtube.com/watch?v=2uaMnEg89bU"},
        {"id":0, "round": 1, "name": "Recovery", "duration": 20, "vis":false},{"id":7,  "round": 3, "name":"Mountain Runners", "duration":30,"vis": true, "link":"https://youtu.be/mYX-NSG2CaQ?si=F_P_g3jqLoD-XDeK"},
        {"id":0, "round": 1, "name": "Recovery", "duration": 20, "vis":false},{"id":8,  "round": 3, "name":"Crunches", "duration":45,"vis": true, "link":"https://www.youtube.com/watch?v=2uaMnEg89bU"},
        {"id":0, "round": 1, "name": "Recovery", "duration": 20, "vis":false},{"id":9,  "round": 3, "name":"Easy Squats", "duration":30,"vis": true, "link":""},
        {"id":0, "round": 1, "name": "Recovery", "duration": 20, "vis":false},{"id":10, "round": 4, "name":"Mountain Climbers Pylo Spider", "duration":30,"vis": true, "link":"https://www.youtube.com/watch?v=2uaMnEg89bU"},
        {"id":0, "round": 1, "name": "Recovery", "duration": 20, "vis":false},{"id":11, "round": 4, "name":"Crunches", "duration":45,"vis": true, "link":""},
        {"id":0, "round": 1, "name": "Recovery", "duration": 20, "vis":false},{"id":12, "round": 4, "name":"Easy Squats", "duration":30,"vis": true, "link":""},
        {"id":0, "round": 1, "name": "Recovery", "duration": 20, "vis":false},{"id":13, "round": 5, "name":"Mountain Side Jumpers", "duration":30,"vis": true, "link":""},
        {"id":0, "round": 1, "name": "Recovery", "duration": 20, "vis":false},{"id":14, "round": 5, "name":"Crunches", "duration":45,"vis": true, "link":""},
        {"id":0, "round": 1, "name": "Recovery", "duration": 20, "vis":false},{"id":15, "round": 5, "name":"Easy Squats", "duration":30,"vis": true, "link":""},
        {"id":0, "round": 1, "name": "Recovery", "duration": 20, "vis":false},{"id":16, "round": 6, "name":"Mountain Wide Jumpers", "duration":30,"vis": true, "link":""},
        {"id":0, "round": 1, "name": "Recovery", "duration": 20, "vis":false},{"id":17, "round": 6, "name":"Crunches", "duration":45,"vis": true, "link":""},
        {"id":0, "round": 1, "name": "Recovery", "duration": 20, "vis":false},{"id":18, "round": 6, "name":"Easy Squats", "duration":30,"vis": true, "link":""}
    ]},
    {
    "id":1,
    "name":"Anthony",
    "level": 2,
    "for": "Ganzkörper",
    "roundsExercises": "6x3",
    "exercises":[
        {"id":0, "round": 1, "name": "Start in", "duration": 10, "vis":false},{"id":1, "round": 1, "name":"Mountain Jumpers", "duration":30,"vis": true, "link":""},
        {"id":0, "round": 1, "name": "Recovery", "duration": 20, "vis":false},{"id":2, "round": 1, "name":"Sit-Ups", "duration":45,"vis": true, "link":""},
        {"id":0, "round": 1, "name": "Recovery", "duration": 20, "vis":false},{"id":3, "round": 1, "name":"Squats", "duration":30,"vis": true, "link":""},
        {"id":0, "round": 1, "name": "Recovery", "duration": 20, "vis":false},{"id":4, "round": 2, "name":"Mountain Climbers", "duration":30,"vis": true, "link":""},
        {"id":0, "round": 1, "name": "Recovery", "duration": 20, "vis":false},{"id":5, "round": 2, "name":"Sit-Ups", "duration":45,"vis": true, "link":""},
        {"id":0, "round": 1, "name": "Recovery", "duration": 20, "vis":false},{"id":6, "round": 2, "name":"Squats", "duration":45,"vis": true, "link":""},
        {"id":0, "round": 1, "name": "Recovery", "duration": 20, "vis":false},{"id":7, "round": 3, "name":"Mountain Runners", "duration":30,"vis": true, "link":""},
        {"id":0, "round": 1, "name": "Recovery", "duration": 20, "vis":false},{"id":8, "round": 3, "name":"Sit-Ups", "duration":45,"vis": true, "link":""},
        {"id":0, "round": 1, "name": "Recovery", "duration": 20, "vis":false},{"id":9, "round": 3, "name":"Squats", "duration":30,"vis": true, "link":""},
        {"id":0, "round": 1, "name": "Recovery", "duration": 20, "vis":false},{"id":10, "round": 4, "name":"Mountain Climbers Pylo Spider", "duration":30,"vis": true, "link":""},
        {"id":0, "round": 1, "name": "Recovery", "duration": 20, "vis":false},{"id":11, "round": 4, "name":"Sit-Ups", "duration":45,"vis": true, "link":""},
        {"id":0, "round": 1, "name": "Recovery", "duration": 20, "vis":false},{"id":12, "round": 4, "name":"Squats", "duration":30,"vis": true, "link":""},
        {"id":0, "round": 1, "name": "Recovery", "duration": 20, "vis":false},{"id":13, "round": 5, "name":"Mountain Side Jumpers", "duration":30,"vis": true, "link":""},
        {"id":0, "round": 1, "name": "Recovery", "duration": 20, "vis":false},{"id":14, "round": 5, "name":"Sit-Ups", "duration":45,"vis": true, "link":""},
        {"id":0, "round": 1, "name": "Recovery", "duration": 20, "vis":false},{"id":15, "round": 5, "name":"Squats", "duration":30,"vis": true, "link":""},
        {"id":0, "round": 1, "name": "Recovery", "duration": 20, "vis":false},{"id":16, "round": 6, "name":"Mountain Wide Jumpers", "duration":30,"vis": true, "link":""},
        {"id":0, "round": 1, "name": "Recovery", "duration": 20, "vis":false},{"id":17, "round": 6, "name":"Sit-Ups", "duration":45,"vis": true, "link":""},
        {"id":0, "round": 1, "name": "Recovery", "duration": 20, "vis":false},{"id":18, "round": 6, "name":"Squats", "duration":30,"vis": true, "link":""}
    ]},{
        "id":2,
        "name":"Anthony",
        "level": 3,
        "for": "Ganzkörper",
        "roundsExercises": "6x3",
        "exercises":[
            {"id":0, "round": 1, "name": "Start in", "duration": 10, "vis":false},{"id":1,  "round": 1, "name":"Mountain Jumpers", "duration":30,"vis": true, "link":""},
            {"id":0, "round": 1, "name": "Recovery", "duration": 20, "vis":false},{"id":2, "round": 1, "name":"Knee Tuck Crunches", "duration":45,"vis": true, "link":""},
            {"id":0, "round": 1, "name": "Recovery", "duration": 20, "vis":false},{"id":3, "round": 1, "name":"Jump Squats", "duration":30,"vis": true, "link":""},
            {"id":0, "round": 1, "name": "Recovery", "duration": 20, "vis":false},{"id":4,  "round": 2, "name":"Mountain Climbers", "duration":30,"vis": true, "link":""},
            {"id":0, "round": 1, "name": "Recovery", "duration": 20, "vis":false},{"id":5, "round": 2, "name":"Knee Tuck Crunches", "duration":45,"vis": true, "link":""},
            {"id":0, "round": 1, "name": "Recovery", "duration": 20, "vis":false},{"id":6, "round": 2, "name":"Jump Squats", "duration":30,"vis": true, "link":""},
            {"id":0, "round": 1, "name": "Recovery", "duration": 20, "vis":false},{"id":7,  "round": 3, "name":"Mountain Runners", "duration":30,"vis": true, "link":""},
            {"id":0, "round": 1, "name": "Recovery", "duration": 20, "vis":false},{"id":8, "round": 3, "name":"Knee Tuck Crunches", "duration":45,"vis": true, "link":""},
            {"id":0, "round": 1, "name": "Recovery", "duration": 20, "vis":false},{"id":9, "round": 3, "name":"Jump Squats", "duration":30,"vis": true, "link":""},
            {"id":0, "round": 1, "name": "Recovery", "duration": 20, "vis":false},{"id":10, "round": 4, "name":"Mountain Climbers Pylo Spider", "duration":30,"vis": true, "link":""},
            {"id":0, "round": 1, "name": "Recovery", "duration": 20, "vis":false},{"id":11, "round": 4, "name":"Knee Tuck Crunches", "duration":45,"vis": true, "link":""},
            {"id":0, "round": 1, "name": "Recovery", "duration": 20, "vis":false},{"id":12, "round": 4, "name":"Jump Squats", "duration":30,"vis": true, "link":""},
            {"id":0, "round": 1, "name": "Recovery", "duration": 20, "vis":false},{"id":13, "round": 5, "name":"Mountain Side Jumpers", "duration":30,"vis": true, "link":""},
            {"id":0, "round": 1, "name": "Recovery", "duration": 20, "vis":false},{"id":14, "round": 5, "name":"Knee Tuck Crunches", "duration":45,"vis": true, "link":""},
            {"id":0, "round": 1, "name": "Recovery", "duration": 20, "vis":false},{"id":15, "round": 5, "name":"Jump Squats", "duration":30,"vis": true, "link":""},
            {"id":0, "round": 1, "name": "Recovery", "duration": 20, "vis":false},{"id":16, "round": 6, "name":"Mountain Wide Jumpers", "duration":30,"vis": true, "link":""},
            {"id":0, "round": 1, "name": "Recovery", "duration": 20, "vis":false},{"id":17, "round": 6, "name":"Knee Tuck Crunches", "duration":45,"vis": true, "link":""},
            {"id":0, "round": 1, "name": "Recovery", "duration": 20, "vis":false},{"id":18, "round": 6, "name":"Jump Squats", "duration":30,"vis": true, "link":""}
        ]},{
        "id":3,
        "name":"Anthony",
        "level": 4,
        "for": "Ganzkörper",
        "roundsExercises": "6x3",
        "exercises":[
            {"id":0, "round": 1, "name": "Start in", "duration": 10, "vis":false},{"id":1, "round": 1, "name":"Mountain Jumpers", "duration":30,"vis": true, "link":""},
            {"id":0, "round": 1, "name": "Recovery", "duration": 20, "vis":false},{"id":10, "round": 1, "name":"Jack Knives", "duration":45,"vis": true, "link":""},
            {"id":0, "round": 1, "name": "Recovery", "duration": 20, "vis":false},{"id":11, "round": 1, "name":"Tuck Jump Squats", "duration":30,"vis": true, "link":""},
            {"id":0, "round": 1, "name": "Recovery", "duration": 20, "vis":false},{"id":4, "round": 2, "name":"Mountain Climbers", "duration":30,"vis": true, "link":""},
            {"id":0, "round": 1, "name": "Recovery", "duration": 20, "vis":false},{"id":10, "round": 2, "name":"Jack Knives", "duration":45,"vis": true, "link":""},
            {"id":0, "round": 1, "name": "Recovery", "duration": 20, "vis":false},{"id":11, "round": 2, "name":"Tuck Jump Squats", "duration":30,"vis": true, "link":""},
            {"id":0, "round": 1, "name": "Recovery", "duration": 20, "vis":false},{"id":4, "round": 3, "name":"Mountain Runners", "duration":30,"vis": true, "link":""},
            {"id":0, "round": 1, "name": "Recovery", "duration": 20, "vis":false},{"id":10, "round": 3, "name":"Jack Knives", "duration":45,"vis": true, "link":""},
            {"id":0, "round": 1, "name": "Recovery", "duration": 20, "vis":false},{"id":11, "round": 3, "name":"Tuck Jump Squats", "duration":30,"vis": true, "link":""},
            {"id":0, "round": 1, "name": "Recovery", "duration": 20, "vis":false},{"id":5, "round": 4, "name":"Mountain Climbers Pylo Spider", "duration":30,"vis": true, "link":""},
            {"id":0, "round": 1, "name": "Recovery", "duration": 20, "vis":false},{"id":10, "round": 4, "name":"Jack Knives", "duration":45,"vis": true, "link":""},
            {"id":0, "round": 1, "name": "Recovery", "duration": 20, "vis":false},{"id":11, "round": 4, "name":"Tuck Jump Squats", "duration":30,"vis": true, "link":""},
            {"id":0, "round": 1, "name": "Recovery", "duration": 20, "vis":false},{"id":6, "round": 5, "name":"Mountain Side Jumpers", "duration":30,"vis": true, "link":""},
            {"id":0, "round": 1, "name": "Recovery", "duration": 20, "vis":false},{"id":10, "round": 5, "name":"Jack Knives", "duration":45,"vis": true, "link":""},
            {"id":0, "round": 1, "name": "Recovery", "duration": 20, "vis":false},{"id":11, "round": 5, "name":"Tuck Jump Squats", "duration":30,"vis": true, "link":""},
            {"id":0, "round": 1, "name": "Recovery", "duration": 20, "vis":false},{"id":1, "round": 6, "name":"Mountain Wide Jumpers", "duration":30,"vis": true, "link":""},
            {"id":0, "round": 1, "name": "Recovery", "duration": 20, "vis":false},{"id":10, "round": 6, "name":"Jack Knives", "duration":45,"vis": true, "link":""},
            {"id":0, "round": 1, "name": "Recovery", "duration": 20, "vis":false},{"id":11, "round": 6, "name":"Tuck Jump Squats", "duration":30,"vis": true, "link":""}
        ]},{
        "id":4,
        "name":"Bernard",
        "level": 1,
        "for": "Oberkörper",
        "roundsExercises": "3x6",
        "exercises":[
            {"id":0, "round": 1, "name": "Start in", "duration": 10, "vis":false},{"id":1, "round": 1, "name":"Bear Crawls", "duration":30,"vis": true, "link":""},
            {"id":0, "round": 1, "name": "Recovery", "duration": 20, "vis":false},{"id":2, "round": 1, "name":"Crunches", "duration":30,"vis": true, "link":""},
            {"id":0, "round": 1, "name": "Recovery", "duration": 20, "vis":false},{"id":3, "round": 1, "name":"Mountain Jumpers", "duration":30,"vis": true, "link":""},
            {"id":0, "round": 1, "name": "Recovery", "duration": 20, "vis":false},{"id":4, "round": 1, "name":"Knee MMA Push-Ups", "duration":30,"vis": true, "link":""},
            {"id":0, "round": 1, "name": "Recovery", "duration": 20, "vis":false},{"id":5, "round": 1, "name":"Triceps Dips", "duration":30,"vis": true, "link":""},
            {"id":0, "round": 1, "name": "Recovery", "duration": 20, "vis":false},{"id":6, "round": 1, "name":"T High Plank", "duration":30,"vis": true, "link":""},
            {"id":0, "round": 1, "name": "Recovery", "duration": 20, "vis":false},{"id":1, "round": 2, "name":"Bear Crawls", "duration":45,"vis": true, "link":""},
            {"id":0, "round": 1, "name": "Recovery", "duration": 20, "vis":false},{"id":2, "round": 2, "name":"Crunches", "duration":45,"vis": true, "link":""},
            {"id":0, "round": 1, "name": "Recovery", "duration": 20, "vis":false},{"id":3, "round": 2, "name":"Mountain Jumpers", "duration":45,"vis": true, "link":""},
            {"id":0, "round": 1, "name": "Recovery", "duration": 20, "vis":false},{"id":4, "round": 2, "name":"Knee MMA Push-Ups", "duration":45,"vis": true, "link":""},
            {"id":0, "round": 1, "name": "Recovery", "duration": 20, "vis":false},{"id":5, "round": 2, "name":"Triceps Dips", "duration":45,"vis": true, "link":""},
            {"id":0, "round": 1, "name": "Recovery", "duration": 20, "vis":false},{"id":6, "round": 2, "name":"T High Plank", "duration":45,"vis": true, "link":""},
            {"id":0, "round": 1, "name": "Recovery", "duration": 20, "vis":false},{"id":1, "round": 3, "name":"Bear Crawls", "duration":30,"vis": true, "link":""},
            {"id":0, "round": 1, "name": "Recovery", "duration": 20, "vis":false},{"id":2, "round": 3, "name":"Crunches", "duration":30,"vis": true, "link":""},
            {"id":0, "round": 1, "name": "Recovery", "duration": 20, "vis":false},{"id":3, "round": 3, "name":"Mountain Jumpers", "duration":30,"vis": true, "link":""},
            {"id":0, "round": 1, "name": "Recovery", "duration": 20, "vis":false},{"id":4, "round": 3, "name":"Knee MMA Push-Ups", "duration":30,"vis": true, "link":""},
            {"id":0, "round": 1, "name": "Recovery", "duration": 20, "vis":false},{"id":5, "round": 3, "name":"Triceps Dips", "duration":30,"vis": true, "link":""},
            {"id":0, "round": 1, "name": "Recovery", "duration": 20, "vis":false},{"id":6, "round": 3, "name":"T High Plank", "duration":30,"vis": true, "link":""}
        ]},{
        "id":5,
        "name":"Bernard",
        "level": 2,
        "for": "Oberkörper",
        "roundsExercises": "3x6",
        "exercises":[
                    {"id":0, "round": 1, "name": "Start in", "duration": 10, "vis":false},{"id":1, "round": 1, "name":"Bear Crawls", "duration":30,"vis": true, "link":""},
                    {"id":0, "round": 1, "name": "Recovery", "duration": 20, "vis":false},{"id":2, "round": 1, "name":"Sit-Ups", "duration":30,"vis": true, "link":""},
                    {"id":0, "round": 1, "name": "Recovery", "duration": 20, "vis":false},{"id":3, "round": 1, "name":"Mountain Climbers", "duration":30,"vis": true, "link":""},
                    {"id":0, "round": 1, "name": "Recovery", "duration": 20, "vis":false},{"id":4, "round": 1, "name":"MMA Push-Ups", "duration":30,"vis": true, "link":""},
                    {"id":0, "round": 1, "name": "Recovery", "duration": 20, "vis":false},{"id":5, "round": 1, "name":"Triceps Dips", "duration":30,"vis": true, "link":""},
                    {"id":0, "round": 1, "name": "Recovery", "duration": 20, "vis":false},{"id":6, "round": 1, "name":"T Low Planks", "duration":30,"vis": true, "link":""},
                    {"id":0, "round": 1, "name": "Recovery", "duration": 20, "vis":false},{"id":1, "round": 2, "name":"Bear Crawls", "duration":45,"vis": true, "link":""},
                    {"id":0, "round": 1, "name": "Recovery", "duration": 20, "vis":false},{"id":2, "round": 2, "name":"Sit-Ups", "duration":45,"vis": true, "link":""},
                    {"id":0, "round": 1, "name": "Recovery", "duration": 20, "vis":false},{"id":3, "round": 2, "name":"Mountain Climbers", "duration":45,"vis": true, "link":""},
                    {"id":0, "round": 1, "name": "Recovery", "duration": 20, "vis":false},{"id":4, "round": 2, "name":"MMA Push-Ups", "duration":45,"vis": true, "link":""},
                    {"id":0, "round": 1, "name": "Recovery", "duration": 20, "vis":false},{"id":5, "round": 2, "name":"Triceps Dips", "duration":45,"vis": true, "link":""},
                    {"id":0, "round": 1, "name": "Recovery", "duration": 20, "vis":false},{"id":6, "round": 2, "name":"T Low Planks", "duration":45,"vis": true, "link":""},
                    {"id":0, "round": 1, "name": "Recovery", "duration": 20, "vis":false},{"id":1, "round": 3, "name":"Bear Crawls", "duration":30,"vis": true, "link":""},
                    {"id":0, "round": 1, "name": "Recovery", "duration": 20, "vis":false},{"id":2, "round": 3, "name":"Sit-Ups", "duration":30,"vis": true, "link":""},
                    {"id":0, "round": 1, "name": "Recovery", "duration": 20, "vis":false},{"id":3, "round": 3, "name":"Mountain Climbers", "duration":30,"vis": true, "link":""},
                    {"id":0, "round": 1, "name": "Recovery", "duration": 20, "vis":false},{"id":4, "round": 3, "name":"MMA Push-Ups", "duration":30,"vis": true, "link":""},
                    {"id":0, "round": 1, "name": "Recovery", "duration": 20, "vis":false},{"id":5, "round": 3, "name":"Triceps Dips", "duration":30,"vis": true, "link":""},
                    {"id":0, "round": 1, "name": "Recovery", "duration": 20, "vis":false},{"id":6, "round": 3, "name":"T Low Planks", "duration":30,"vis": true, "link":""}
        ]},{
        "id":6,
        "name":"Bernard",
        "level": 3,
        "for": "Oberkörper",
        "roundsExercises": "3x6",
        "exercises":[
                    {"id":0, "round": 1, "name": "Start in", "duration": 10, "vis":false},{"id":1, "round": 1, "name":"Spiderman Walk", "duration":30,"vis": true, "link":""},
                    {"id":0, "round": 1, "name": "Recovery", "duration": 20, "vis":false},{"id":2, "round": 1, "name":"Knee Tuck Crunches", "duration":30,"vis": true, "link":""},
                    {"id":0, "round": 1, "name": "Recovery", "duration": 20, "vis":false},{"id":3, "round": 1, "name":"Mountain Side Jumpers", "duration":30,"vis": true, "link":""},
                    {"id":0, "round": 1, "name": "Recovery", "duration": 20, "vis":false},{"id":4, "round": 1, "name":"Low Plank Pop-Ups", "duration":30,"vis": true, "link":""},
                    {"id":0, "round": 1, "name": "Recovery", "duration": 20, "vis":false},{"id":5, "round": 1, "name":"Triceps Dips", "duration":30,"vis": true, "link":""},
                    {"id":0, "round": 1, "name": "Recovery", "duration": 20, "vis":false},{"id":6, "round": 1, "name":"T Push-Ups", "duration":30,"vis": true, "link":""},
                    {"id":0, "round": 1, "name": "Recovery", "duration": 20, "vis":false},{"id":1, "round": 2, "name":"Spiderman Walk", "duration":45,"vis": true, "link":""},
                    {"id":0, "round": 1, "name": "Recovery", "duration": 20, "vis":false},{"id":2, "round": 2, "name":"Knee Tuck Crunches", "duration":45,"vis": true, "link":""},
                    {"id":0, "round": 1, "name": "Recovery", "duration": 20, "vis":false},{"id":3, "round": 2, "name":"Mountain Side Jumpers", "duration":45,"vis": true, "link":""},
                    {"id":0, "round": 1, "name": "Recovery", "duration": 20, "vis":false},{"id":4, "round": 2, "name":"Low Plank Pop-Ups", "duration":45,"vis": true, "link":""},
                    {"id":0, "round": 1, "name": "Recovery", "duration": 20, "vis":false},{"id":5, "round": 2, "name":"Triceps Dips", "duration":45,"vis": true, "link":""},
                    {"id":0, "round": 1, "name": "Recovery", "duration": 20, "vis":false},{"id":6, "round": 2, "name":"T Push-Ups", "duration":45,"vis": true, "link":""},
                    {"id":0, "round": 1, "name": "Recovery", "duration": 20, "vis":false},{"id":1, "round": 3, "name":"Spiderman Walk", "duration":30,"vis": true, "link":""},
                    {"id":0, "round": 1, "name": "Recovery", "duration": 20, "vis":false},{"id":2, "round": 3, "name":"Knee Tuck Crunches", "duration":30,"vis": true, "link":""},
                    {"id":0, "round": 1, "name": "Recovery", "duration": 20, "vis":false},{"id":3, "round": 3, "name":"Mountain Side Jumpers", "duration":30,"vis": true, "link":""},
                    {"id":0, "round": 1, "name": "Recovery", "duration": 20, "vis":false},{"id":4, "round": 3, "name":"Low Plank Pop-Ups", "duration":30,"vis": true, "link":""},
                    {"id":0, "round": 1, "name": "Recovery", "duration": 20, "vis":false},{"id":5, "round": 3, "name":"Triceps Dips", "duration":30,"vis": true, "link":""},
                    {"id":0, "round": 1, "name": "Recovery", "duration": 20, "vis":false},{"id":6, "round": 3, "name":"T Push-Ups", "duration":30,"vis": true, "link":""}
        ]},{
        "id":7,
        "name":"Bernard",
        "level": 4,
        "for": "Oberkörper",
        "roundsExercises": "3x6",
        "exercises":[
                    {"id":0, "round": 1, "name": "Start in", "duration": 10, "vis":false},{"id":1, "round": 1, "name":"Spiderman Walk", "duration":30,"vis": true, "link":""},
                    {"id":0, "round": 1, "name": "Recovery", "duration": 20, "vis":false},{"id":2, "round": 1, "name":"Jack Knives", "duration":30,"vis": true, "link":""},
                    {"id":0, "round": 1, "name": "Recovery", "duration": 20, "vis":false},{"id":3, "round": 1, "name":"Mountain Wide Jumpers", "duration":30,"vis": true, "link":""},
                    {"id":0, "round": 1, "name": "Recovery", "duration": 20, "vis":false},{"id":4, "round": 1, "name":"Triceps Extension Push-Ups", "duration":30,"vis": true, "link":""},
                    {"id":0, "round": 1, "name": "Recovery", "duration": 20, "vis":false},{"id":5, "round": 1, "name":"Triceps Dips", "duration":30,"vis": true, "link":""},
                    {"id":0, "round": 1, "name": "Recovery", "duration": 20, "vis":false},{"id":6, "round": 1, "name":"T Push-Ups", "duration":30,"vis": true, "link":""},
                    {"id":0, "round": 1, "name": "Recovery", "duration": 20, "vis":false},{"id":1, "round": 2, "name":"Spiderman Walk", "duration":45,"vis": true, "link":""},
                    {"id":0, "round": 1, "name": "Recovery", "duration": 20, "vis":false},{"id":2, "round": 2, "name":"Jack Knives", "duration":45,"vis": true, "link":""},
                    {"id":0, "round": 1, "name": "Recovery", "duration": 20, "vis":false},{"id":3, "round": 2, "name":"Mountain Wide Jumpers", "duration":45,"vis": true, "link":""},
                    {"id":0, "round": 1, "name": "Recovery", "duration": 20, "vis":false},{"id":4, "round": 2, "name":"Triceps Extension Push-Ups", "duration":45,"vis": true, "link":""},
                    {"id":0, "round": 1, "name": "Recovery", "duration": 20, "vis":false},{"id":5, "round": 2, "name":"Triceps Dips", "duration":45,"vis": true, "link":""},
                    {"id":0, "round": 1, "name": "Recovery", "duration": 20, "vis":false},{"id":6, "round": 2, "name":"T Push-Ups", "duration":45,"vis": true, "link":""},
                    {"id":0, "round": 1, "name": "Recovery", "duration": 20, "vis":false},{"id":1, "round": 3, "name":"Spiderman Walk", "duration":30,"vis": true, "link":""},
                    {"id":0, "round": 1, "name": "Recovery", "duration": 20, "vis":false},{"id":2, "round": 3, "name":"Jack Knives", "duration":30,"vis": true, "link":""},
                    {"id":0, "round": 1, "name": "Recovery", "duration": 20, "vis":false},{"id":3, "round": 3, "name":"Mountain Wide Jumpers", "duration":30,"vis": true, "link":""},
                    {"id":0, "round": 1, "name": "Recovery", "duration": 20, "vis":false},{"id":4, "round": 3, "name":"Triceps Extension Push-Ups", "duration":30,"vis": true, "link":""},
                    {"id":0, "round": 1, "name": "Recovery", "duration": 20, "vis":false},{"id":5, "round": 3, "name":"Triceps Dips", "duration":30,"vis": true, "link":""},
                    {"id":0, "round": 1, "name": "Recovery", "duration": 20, "vis":false},{"id":6, "round": 3, "name":"T Push-Ups", "duration":30,"vis": true, "link":""}
        ]},{
        "id":8,
        "name":"Canelo",
        "level": 1,
        "for": "Ganzkörper",
        "roundsExercises": "3x10",
        "exercises":[
                    {"id":0, "round": 1, "name": "Start in", "duration": 10, "vis":false},{"id":1, "round": 1, "name":"Jumping Jacks", "duration":60,"vis": true, "link":""},
                    {"id":0, "round": 1, "name": "Recovery", "duration": 20, "vis":false},{"id":2, "round": 1, "name":"Crunches", "duration":40,"vis": true, "link":""},
                    {"id":0, "round": 1, "name": "Recovery", "duration": 20, "vis":false},{"id":3, "round": 1, "name":"Easy Standups", "duration":40,"vis": true, "link":""},
                    {"id":0, "round": 1, "name": "Recovery", "duration": 20, "vis":false},{"id":4, "round": 1, "name":"High Plank Knee Tap", "duration":40,"vis": true, "link":""},
                    {"id":0, "round": 1, "name": "Recovery", "duration": 20, "vis":false},{"id":5, "round": 1, "name":"Easy Squats", "duration":40,"vis": true, "link":""},
                    {"id":0, "round": 1, "name": "Recovery", "duration": 20, "vis":false},{"id":6, "round": 1, "name":"Single Leg Raises", "duration":40,"vis": true, "link":""},
                    {"id":0, "round": 1, "name": "Recovery", "duration": 20, "vis":false},{"id":6, "round": 1, "name":"Easy Squats", "duration":40,"vis": true, "link":""},
                    {"id":0, "round": 1, "name": "Recovery", "duration": 20, "vis":false},{"id":6, "round": 1, "name":"Easy Scissors Kicks", "duration":40,"vis": true, "link":""},
                    {"id":0, "round": 1, "name": "Recovery", "duration": 20, "vis":false},{"id":6, "round": 1, "name":"Quick Feet Squats", "duration":40,"vis": true, "link":""},
                    {"id":0, "round": 1, "name": "Recovery", "duration": 20, "vis":false},{"id":6, "round": 1, "name":"Bicycles", "duration":40,"vis": true, "link":""},
                    {"id":0, "round": 1, "name": "Recovery", "duration": 20, "vis":false},{"id":1, "round": 2, "name":"Jumping Jacks", "duration":55,"vis": true, "link":""},
                    {"id":0, "round": 1, "name": "Recovery", "duration": 20, "vis":false},{"id":2, "round": 2, "name":"Crunches", "duration":35,"vis": true, "link":""},
                    {"id":0, "round": 1, "name": "Recovery", "duration": 20, "vis":false},{"id":3, "round": 2, "name":"Easy Standups", "duration":35,"vis": true, "link":""},
                    {"id":0, "round": 1, "name": "Recovery", "duration": 20, "vis":false},{"id":4, "round": 2, "name":"High Plank Knee Tap", "duration":35,"vis": true, "link":""},
                    {"id":0, "round": 1, "name": "Recovery", "duration": 20, "vis":false},{"id":5, "round": 2, "name":"Easy Squats", "duration":35,"vis": true, "link":""},
                    {"id":0, "round": 1, "name": "Recovery", "duration": 20, "vis":false},{"id":6, "round": 2, "name":"Single Leg Raises", "duration":35,"vis": true, "link":""},
                    {"id":0, "round": 1, "name": "Recovery", "duration": 20, "vis":false},{"id":6, "round": 2, "name":"Easy Squats", "duration":35,"vis": true, "link":""},
                    {"id":0, "round": 1, "name": "Recovery", "duration": 20, "vis":false},{"id":6, "round": 2, "name":"Easy Scissors Kicks", "duration":35,"vis": true, "link":""},
                    {"id":0, "round": 1, "name": "Recovery", "duration": 20, "vis":false},{"id":6, "round": 2, "name":"Quick Feet Squats", "duration":35,"vis": true, "link":""},
                    {"id":0, "round": 1, "name": "Recovery", "duration": 20, "vis":false},{"id":6, "round": 2, "name":"Bicycles", "duration":35,"vis": true, "link":""},
                    {"id":0, "round": 1, "name": "Recovery", "duration": 20, "vis":false},{"id":1, "round": 3, "name":"Jumping Jacks", "duration":50,"vis": true, "link":""},
                    {"id":0, "round": 1, "name": "Recovery", "duration": 20, "vis":false},{"id":2, "round": 3, "name":"Crunches", "duration":30,"vis": true, "link":""},
                    {"id":0, "round": 1, "name": "Recovery", "duration": 20, "vis":false},{"id":3, "round": 3, "name":"Easy Standups", "duration":30,"vis": true, "link":""},
                    {"id":0, "round": 1, "name": "Recovery", "duration": 20, "vis":false},{"id":4, "round": 3, "name":"High Plank Knee Tap", "duration":30,"vis": true, "link":""},
                    {"id":0, "round": 1, "name": "Recovery", "duration": 20, "vis":false},{"id":5, "round": 3, "name":"Easy Squats", "duration":30,"vis": true, "link":""},
                    {"id":0, "round": 1, "name": "Recovery", "duration": 20, "vis":false},{"id":6, "round": 3, "name":"Single Leg Raises", "duration":30,"vis": true, "link":""},
                    {"id":0, "round": 1, "name": "Recovery", "duration": 20, "vis":false},{"id":6, "round": 3, "name":"Easy Squats", "duration":30,"vis": true, "link":""},
                    {"id":0, "round": 1, "name": "Recovery", "duration": 20, "vis":false},{"id":6, "round": 3, "name":"Easy Scissors Kicks", "duration":30,"vis": true, "link":""},
                    {"id":0, "round": 1, "name": "Recovery", "duration": 20, "vis":false},{"id":6, "round": 3, "name":"Quick Feet Squats", "duration":30,"vis": true, "link":""},
                    {"id":0, "round": 1, "name": "Recovery", "duration": 20, "vis":false},{"id":6, "round": 3, "name":"Bicycles", "duration":30,"vis": true, "link":""}
        ]},
        {
        "id":9,
        "name":"Canelo",
        "level": 2,
        "for": "Ganzkörper",
        "roundsExercises": "3x10",
        "exercises":[
                    {"id":0, "round": 1, "name": "Start in", "duration": 10, "vis":false},{"id":1, "round": 1, "name":"Jumping Jacks", "duration":60,"vis": true, "link":""},
                    {"id":0, "round": 1, "name": "Recovery", "duration": 20, "vis":false},{"id":2, "round": 1, "name":"Sit-Ups", "duration":40,"vis": true, "link":""},
                    {"id":0, "round": 1, "name": "Recovery", "duration": 20, "vis":false},{"id":3, "round": 1, "name":"Standups", "duration":40,"vis": true, "link":""},
                    {"id":0, "round": 1, "name": "Recovery", "duration": 20, "vis":false},{"id":4, "round": 1, "name":"High Plank Crunches", "duration":40,"vis": true, "link":""},
                    {"id":0, "round": 1, "name": "Recovery", "duration": 20, "vis":false},{"id":5, "round": 1, "name":"Drop Squats", "duration":40,"vis": true, "link":""},
                    {"id":0, "round": 1, "name": "Recovery", "duration": 20, "vis":false},{"id":6, "round": 1, "name":"Easy Leg Raises", "duration":40,"vis": true, "link":""},
                    {"id":0, "round": 1, "name": "Recovery", "duration": 20, "vis":false},{"id":6, "round": 1, "name":"Squats", "duration":40,"vis": true, "link":""},
                    {"id":0, "round": 1, "name": "Recovery", "duration": 20, "vis":false},{"id":6, "round": 1, "name":"Scissor Kicks", "duration":40,"vis": true, "link":""},
                    {"id":0, "round": 1, "name": "Recovery", "duration": 20, "vis":false},{"id":6, "round": 1, "name":"Quick Feet Squats", "duration":40,"vis": true, "link":""},
                    {"id":0, "round": 1, "name": "Recovery", "duration": 20, "vis":false},{"id":6, "round": 1, "name":"Easy Bicycle Crunches", "duration":40,"vis": true, "link":""},
                    {"id":0, "round": 1, "name": "Recovery", "duration": 20, "vis":false},{"id":1, "round": 2, "name":"Jumping Jacks", "duration":55,"vis": true, "link":""},
                    {"id":0, "round": 1, "name": "Recovery", "duration": 20, "vis":false},{"id":2, "round": 2, "name":"Sit-Ups", "duration":35,"vis": true, "link":""},
                    {"id":0, "round": 1, "name": "Recovery", "duration": 20, "vis":false},{"id":3, "round": 2, "name":"Standups", "duration":35,"vis": true, "link":""},
                    {"id":0, "round": 1, "name": "Recovery", "duration": 20, "vis":false},{"id":4, "round": 2, "name":"High Plank Crunches", "duration":35,"vis": true, "link":""},
                    {"id":0, "round": 1, "name": "Recovery", "duration": 20, "vis":false},{"id":5, "round": 2, "name":"Drop Squats", "duration":35,"vis": true, "link":""},
                    {"id":0, "round": 1, "name": "Recovery", "duration": 20, "vis":false},{"id":6, "round": 2, "name":"Easy Leg Raises", "duration":35,"vis": true, "link":""},
                    {"id":0, "round": 1, "name": "Recovery", "duration": 20, "vis":false},{"id":6, "round": 2, "name":"Squats", "duration":35,"vis": true, "link":""},
                    {"id":0, "round": 1, "name": "Recovery", "duration": 20, "vis":false},{"id":6, "round": 2, "name":"Scissor Kicks", "duration":35,"vis": true, "link":""},
                    {"id":0, "round": 1, "name": "Recovery", "duration": 20, "vis":false},{"id":6, "round": 2, "name":"Quick Feet Squats", "duration":35,"vis": true, "link":""},
                    {"id":0, "round": 1, "name": "Recovery", "duration": 20, "vis":false},{"id":6, "round": 2, "name":"Easy Bicycle Crunches", "duration":35,"vis": true, "link":""},
                    {"id":0, "round": 1, "name": "Recovery", "duration": 20, "vis":false},{"id":1, "round": 3, "name":"Jumping Jacks", "duration":50,"vis": true, "link":""},
                    {"id":0, "round": 1, "name": "Recovery", "duration": 20, "vis":false},{"id":2, "round": 3, "name":"Sit-Ups", "duration":30,"vis": true, "link":""},
                    {"id":0, "round": 1, "name": "Recovery", "duration": 20, "vis":false},{"id":3, "round": 3, "name":"Standups", "duration":30,"vis": true, "link":""},
                    {"id":0, "round": 1, "name": "Recovery", "duration": 20, "vis":false},{"id":4, "round": 3, "name":"High Plank Crunches", "duration":30,"vis": true, "link":""},
                    {"id":0, "round": 1, "name": "Recovery", "duration": 20, "vis":false},{"id":5, "round": 3, "name":"Drop Squats", "duration":30,"vis": true, "link":""},
                    {"id":0, "round": 1, "name": "Recovery", "duration": 20, "vis":false},{"id":6, "round": 3, "name":"Easy Leg Raises", "duration":30,"vis": true, "link":""},
                    {"id":0, "round": 1, "name": "Recovery", "duration": 20, "vis":false},{"id":6, "round": 3, "name":"Squats", "duration":30,"vis": true, "link":""},
                    {"id":0, "round": 1, "name": "Recovery", "duration": 20, "vis":false},{"id":6, "round": 3, "name":"Scissor Kicks", "duration":30,"vis": true, "link":""},
                    {"id":0, "round": 1, "name": "Recovery", "duration": 20, "vis":false},{"id":6, "round": 3, "name":"Quick Feet Squats", "duration":30,"vis": true, "link":""},
                    {"id":0, "round": 1, "name": "Recovery", "duration": 20, "vis":false},{"id":6, "round": 3, "name":"Easy Bicycle Crunches", "duration":30,"vis": true, "link":""}
        ]},
        {
        "id":10,
        "name":"Canelo",
        "level": 3,
        "for": "Ganzkörper",
        "roundsExercises": "3x10",
        "exercises":[
                    {"id":0, "round": 1, "name": "Start in", "duration": 10, "vis":false},{"id":1, "round": 1, "name":"Jumping Jacks", "duration":60,"vis": true, "link":""},
                    {"id":0, "round": 1, "name": "Recovery", "duration": 20, "vis":false},{"id":2, "round": 1, "name":"Knee Tuck Crunches", "duration":40,"vis": true, "link":""},
                    {"id":0, "round": 1, "name": "Recovery", "duration": 20, "vis":false},{"id":3, "round": 1, "name":"Standup Tuck Jumps", "duration":40,"vis": true, "link":""},
                    {"id":0, "round": 1, "name": "Recovery", "duration": 20, "vis":false},{"id":4, "round": 1, "name":"Low Plank Crunches", "duration":40,"vis": true, "link":""},
                    {"id":0, "round": 1, "name": "Recovery", "duration": 20, "vis":false},{"id":5, "round": 1, "name":"In & Out Squats", "duration":40,"vis": true, "link":""},
                    {"id":0, "round": 1, "name": "Recovery", "duration": 20, "vis":false},{"id":6, "round": 1, "name":"Leg Raises", "duration":40,"vis": true, "link":""},
                    {"id":0, "round": 1, "name": "Recovery", "duration": 20, "vis":false},{"id":6, "round": 1, "name":"Jump Squats", "duration":40,"vis": true, "link":""},
                    {"id":0, "round": 1, "name": "Recovery", "duration": 20, "vis":false},{"id":6, "round": 1, "name":"Sitting Scissor Kicks", "duration":40,"vis": true, "link":""},
                    {"id":0, "round": 1, "name": "Recovery", "duration": 20, "vis":false},{"id":6, "round": 1, "name":"Quick Feet Squats", "duration":40,"vis": true, "link":""},
                    {"id":0, "round": 1, "name": "Recovery", "duration": 20, "vis":false},{"id":6, "round": 1, "name":"Bicycle Crunches", "duration":40,"vis": true, "link":""},
                    {"id":0, "round": 1, "name": "Recovery", "duration": 20, "vis":false},{"id":1, "round": 2, "name":"Jumping Jacks", "duration":55,"vis": true, "link":""},
                    {"id":0, "round": 1, "name": "Recovery", "duration": 20, "vis":false},{"id":2, "round": 2, "name":"Knee Tuck Crunches", "duration":35,"vis": true, "link":""},
                    {"id":0, "round": 1, "name": "Recovery", "duration": 20, "vis":false},{"id":3, "round": 2, "name":"Standup Tuck Jumps", "duration":35,"vis": true, "link":""},
                    {"id":0, "round": 1, "name": "Recovery", "duration": 20, "vis":false},{"id":4, "round": 2, "name":"Low Plank Crunches", "duration":35,"vis": true, "link":""},
                    {"id":0, "round": 1, "name": "Recovery", "duration": 20, "vis":false},{"id":5, "round": 2, "name":"In & Out Squats", "duration":35,"vis": true, "link":""},
                    {"id":0, "round": 1, "name": "Recovery", "duration": 20, "vis":false},{"id":6, "round": 2, "name":"Leg Raises", "duration":35,"vis": true, "link":""},
                    {"id":0, "round": 1, "name": "Recovery", "duration": 20, "vis":false},{"id":6, "round": 2, "name":"Jump Squats", "duration":35,"vis": true, "link":""},
                    {"id":0, "round": 1, "name": "Recovery", "duration": 20, "vis":false},{"id":6, "round": 2, "name":"Sitting Scissor Kicks", "duration":35,"vis": true, "link":""},
                    {"id":0, "round": 1, "name": "Recovery", "duration": 20, "vis":false},{"id":6, "round": 2, "name":"Quick Feet Squats", "duration":35,"vis": true, "link":""},
                    {"id":0, "round": 1, "name": "Recovery", "duration": 20, "vis":false},{"id":6, "round": 2, "name":"Bicycle Crunches", "duration":35,"vis": true, "link":""},
                    {"id":0, "round": 1, "name": "Recovery", "duration": 20, "vis":false},{"id":1, "round": 3, "name":"Jumping Jacks", "duration":50,"vis": true, "link":""},
                    {"id":0, "round": 1, "name": "Recovery", "duration": 20, "vis":false},{"id":2, "round": 3, "name":"Knee Tuck Crunches", "duration":30,"vis": true, "link":""},
                    {"id":0, "round": 1, "name": "Recovery", "duration": 20, "vis":false},{"id":3, "round": 3, "name":"Standup Tuck Jumps", "duration":30,"vis": true, "link":""},
                    {"id":0, "round": 1, "name": "Recovery", "duration": 20, "vis":false},{"id":4, "round": 3, "name":"Low Plank Crunches", "duration":30,"vis": true, "link":""},
                    {"id":0, "round": 1, "name": "Recovery", "duration": 20, "vis":false},{"id":5, "round": 3, "name":"In & Out Squats", "duration":30,"vis": true, "link":""},
                    {"id":0, "round": 1, "name": "Recovery", "duration": 20, "vis":false},{"id":6, "round": 3, "name":"Leg Raises", "duration":30,"vis": true, "link":""},
                    {"id":0, "round": 1, "name": "Recovery", "duration": 20, "vis":false},{"id":6, "round": 3, "name":"Jump Squats", "duration":30,"vis": true, "link":""},
                    {"id":0, "round": 1, "name": "Recovery", "duration": 20, "vis":false},{"id":6, "round": 3, "name":"Sitting Scissor Kicks", "duration":30,"vis": true, "link":""},
                    {"id":0, "round": 1, "name": "Recovery", "duration": 20, "vis":false},{"id":6, "round": 3, "name":"Quick Feet Squats", "duration":30,"vis": true, "link":""},
                    {"id":0, "round": 1, "name": "Recovery", "duration": 20, "vis":false},{"id":6, "round": 3, "name":"Bicycle Crunches", "duration":30,"vis": true, "link":""}
        ]},
        {
        "id":11,
        "name":"Canelo",
        "level": 4,
        "for": "Ganzkörper",
        "roundsExercises": "3x10",
        "exercises":[
                    {"id":0, "round": 1, "name": "Start in", "duration": 10, "vis":false},{"id":1, "round": 1, "name":"Jumping Jacks", "duration":60,"vis": true, "link":""},
                    {"id":0, "round": 1, "name": "Recovery", "duration": 20, "vis":false},{"id":2, "round": 1, "name":"Jack Knives", "duration":40,"vis": true, "link":""},
                    {"id":0, "round": 1, "name": "Recovery", "duration": 20, "vis":false},{"id":3, "round": 1, "name":"Pistol Standups", "duration":40,"vis": true, "link":""},
                    {"id":0, "round": 1, "name": "Recovery", "duration": 20, "vis":false},{"id":4, "round": 1, "name":"Oush-Up Toe Tap", "duration":40,"vis": true, "link":""},
                    {"id":0, "round": 1, "name": "Recovery", "duration": 20, "vis":false},{"id":5, "round": 1, "name":"180 Jump Squats", "duration":40,"vis": true, "link":""},
                    {"id":0, "round": 1, "name": "Recovery", "duration": 20, "vis":false},{"id":6, "round": 1, "name":"Sitting Leg Raises", "duration":40,"vis": true, "link":""},
                    {"id":0, "round": 1, "name": "Recovery", "duration": 20, "vis":false},{"id":6, "round": 1, "name":"Tuck Jump Squats", "duration":40,"vis": true, "link":""},
                    {"id":0, "round": 1, "name": "Recovery", "duration": 20, "vis":false},{"id":6, "round": 1, "name":"Sitting Scissor Kicks High Legs", "duration":40,"vis": true, "link":""},
                    {"id":0, "round": 1, "name": "Recovery", "duration": 20, "vis":false},{"id":6, "round": 1, "name":"Quick Feet Squats", "duration":40,"vis": true, "link":""},
                    {"id":0, "round": 1, "name": "Recovery", "duration": 20, "vis":false},{"id":6, "round": 1, "name":"Bicycle Sit-Ups", "duration":40,"vis": true, "link":""},
                    {"id":0, "round": 1, "name": "Recovery", "duration": 20, "vis":false},{"id":1, "round": 2, "name":"Jumping Jacks", "duration":55,"vis": true, "link":""},
                    {"id":0, "round": 1, "name": "Recovery", "duration": 20, "vis":false},{"id":2, "round": 2, "name":"Jack Knives", "duration":35,"vis": true, "link":""},
                    {"id":0, "round": 1, "name": "Recovery", "duration": 20, "vis":false},{"id":3, "round": 2, "name":"Pistol Standups", "duration":35,"vis": true, "link":""},
                    {"id":0, "round": 1, "name": "Recovery", "duration": 20, "vis":false},{"id":4, "round": 2, "name":"Oush-Up Toe Tap", "duration":35,"vis": true, "link":""},
                    {"id":0, "round": 1, "name": "Recovery", "duration": 20, "vis":false},{"id":5, "round": 2, "name":"180 Jump Squats", "duration":35,"vis": true, "link":""},
                    {"id":0, "round": 1, "name": "Recovery", "duration": 20, "vis":false},{"id":6, "round": 2, "name":"Sitting Leg Raises", "duration":35,"vis": true, "link":""},
                    {"id":0, "round": 1, "name": "Recovery", "duration": 20, "vis":false},{"id":6, "round": 2, "name":"Tuck Jump Squats", "duration":35,"vis": true, "link":""},
                    {"id":0, "round": 1, "name": "Recovery", "duration": 20, "vis":false},{"id":6, "round": 2, "name":"Sitting Scissor Kicks High Legs", "duration":35,"vis": true, "link":""},
                    {"id":0, "round": 1, "name": "Recovery", "duration": 20, "vis":false},{"id":6, "round": 2, "name":"Quick Feet Squats", "duration":35,"vis": true, "link":""},
                    {"id":0, "round": 1, "name": "Recovery", "duration": 20, "vis":false},{"id":6, "round": 2, "name":"Bicycle Sit-Ups", "duration":35,"vis": true, "link":""},
                    {"id":0, "round": 1, "name": "Recovery", "duration": 20, "vis":false},{"id":1, "round": 3, "name":"Jumping Jacks", "duration":50,"vis": true, "link":""},
                    {"id":0, "round": 1, "name": "Recovery", "duration": 20, "vis":false},{"id":2, "round": 3, "name":"Jack Knives", "duration":30,"vis": true, "link":""},
                    {"id":0, "round": 1, "name": "Recovery", "duration": 20, "vis":false},{"id":3, "round": 3, "name":"Pistol Standups", "duration":30,"vis": true, "link":""},
                    {"id":0, "round": 1, "name": "Recovery", "duration": 20, "vis":false},{"id":4, "round": 3, "name":"Oush-Up Toe Tap", "duration":30,"vis": true, "link":""},
                    {"id":0, "round": 1, "name": "Recovery", "duration": 20, "vis":false},{"id":5, "round": 3, "name":"180 Jump Squats", "duration":30,"vis": true, "link":""},
                    {"id":0, "round": 1, "name": "Recovery", "duration": 20, "vis":false},{"id":6, "round": 3, "name":"Sitting Leg Raises", "duration":30,"vis": true, "link":""},
                    {"id":0, "round": 1, "name": "Recovery", "duration": 20, "vis":false},{"id":6, "round": 3, "name":"Tuck Jump Squats", "duration":30,"vis": true, "link":""},
                    {"id":0, "round": 1, "name": "Recovery", "duration": 20, "vis":false},{"id":6, "round": 3, "name":"Sitting Scissor Kicks High Legs", "duration":30,"vis": true, "link":""},
                    {"id":0, "round": 1, "name": "Recovery", "duration": 20, "vis":false},{"id":6, "round": 3, "name":"Quick Feet Squats", "duration":30,"vis": true, "link":""},
                    {"id":0, "round": 1, "name": "Recovery", "duration": 20, "vis":false},{"id":6, "round": 3, "name":"Bicycle Sit-Ups", "duration":30,"vis": true, "link":""}
        ]}
    ]}
